module/__init__.py
module/add.py
module/smart_substract.py
module/subtract.py
module/extras/__init__.py
module/extras/divide.py
module/extras/multiply.py
module/extras/smart_divide.py
package_tut-0.0.1.dist-info/METADATA
package_tut-0.0.1.dist-info/WHEEL
package_tut-0.0.1.dist-info/top_level.txt
package_tut-0.0.1.dist-info/RECORD
